lisa/__init__.py
lisa/_version.py
lisa/cli/__init__.py
lisa/cli/cli.py
lisa/cli/test_cli.py
lisa/core/__init__.py
lisa/core/assays.py
lisa/core/config.ini
lisa/core/data_interface.py
lisa/core/gene_selection.py
lisa/core/genome_tools.py
lisa/core/h5_config.ini
lisa/core/io.py
lisa/core/lisa_core.py
lisa/core/utils.py
lisa/genomes/hg38.genome
lisa/genomes/hg38.refseq
lisa/genomes/mm10.genome
lisa/genomes/mm10.refseq
lisa/lisa_public_data/__init__.py
lisa/lisa_public_data/assays.py
lisa/lisa_public_data/config.ini
lisa/lisa_public_data/genes_test.py
lisa/lisa_public_data/models.py
lisa/lisa_user_data/__init__.py
lisa/lisa_user_data/assays.py
lisa/lisa_user_data/bam_test.py
lisa/lisa_user_data/config.ini
lisa/lisa_user_data/coverage_test.py
lisa/lisa_user_data/regions_test.py
lisa2-2.3.2.dist-info/LICENSE
lisa2-2.3.2.dist-info/METADATA
lisa2-2.3.2.dist-info/WHEEL
lisa2-2.3.2.dist-info/entry_points.txt
lisa2-2.3.2.dist-info/top_level.txt
lisa2-2.3.2.dist-info/zip-safe
lisa2-2.3.2.dist-info/RECORD
