Metadata-Version: 2.1
Name: lisa2
Version: 2.3.2
Summary: Lisa: inferring transcriptional regulators through integrative modeling of public chromatin accessibility and ChIP-seq data. X. Shirley Liu Lab, 2020
Home-page: https://genomebiology.biomedcentral.com/articles/10.1186/s13059-020-1934-6
License: BSD3 License
Classifier: License :: OSI Approved :: BSD License
Classifier: Environment :: Console
Classifier: Intended Audience :: Science/Research
Classifier: Natural Language :: English
Classifier: Operating System :: MacOS :: MacOS X
Classifier: Operating System :: POSIX :: Linux
Classifier: Programming Language :: Python :: 3
Classifier: Programming Language :: Python :: 3.7
Classifier: Programming Language :: Python :: 3.8
Classifier: Programming Language :: Python :: 3.9
Classifier: Programming Language :: Python :: 3.6
Classifier: Programming Language :: Python :: 3.5
Requires-Python: >=3.5
License-File: LICENSE
Requires-Dist: numpy <2,>=1.17
Requires-Dist: scipy <2,>=1.4
Requires-Dist: h5py >=2
Requires-Dist: scikit-learn <2,>=0.22
Provides-Extra: coverage
Requires-Dist: pyBigWig <1,>=0.3 ; extra == 'coverage'
